srf_attention/__init__.py
srf_attention/att.py
srf_attention/kernel.py
srf_attention/rfs.py
srf_attention/torch_low_mem_attn.py
srf_attention-1.0.16.dist-info/LICENSE
srf_attention-1.0.16.dist-info/METADATA
srf_attention-1.0.16.dist-info/WHEEL
srf_attention-1.0.16.dist-info/top_level.txt
srf_attention-1.0.16.dist-info/RECORD
