Metadata-Version: 2.1
Name: srf-attention
Version: 1.0.16
Summary: Simplex random feature attention in PyTorch for both training and inference
Home-page: https://github.com/alexjlevenston/srf-attention
Author: Alex Levenston
Author-email: alexlevenston2021@gmail.com
License: MIT
Classifier: License :: OSI Approved :: MIT License
Classifier: Programming Language :: Python :: 3
Classifier: Topic :: Software Development :: Libraries :: Python Modules
Requires-Python: >=3.6
License-File: LICENSE
Requires-Dist: torch
Requires-Dist: scipy
Requires-Dist: einops
